Workbook

Sheet Como usar
A1: AUDITORIA DE CAMPANHAS — TRÁFEGO PAGO
A2: V4 Company · Como usar esta auditoria
B4: Para que serve
B5: • Auditar contas de mídia paga (Meta, Google, LinkedIn, TikTok) de forma padronizada.
B6: • Identificar erros, oportunidades de otimização e pontos de escala antes e durante a operação.
B7: • Serve sozinha (sem IA) ou como base para a auditoria assistida do Blackbox.
B9: Passo a passo
B10: 1. Preencha o topo com contexto do cliente (investimento, ticket, produto) nas Observações se quiser.
B11: 2. Comece pela aba Fundamentos (vale para todos os canais).
B12: 3. Depois audite cada canal ativo na aba correspondente. Pule canais que o cliente não usa (marque N/A).
B13: 4. Para cada item: leia 'Como auditar', compare com o 'Benchmark', defina o Status e anote em Observações.
B14: 5. Quando o Status for Ajustar/Crítico, registre o plano na coluna 'Como corrigir' como guia.
B15: 6. Acompanhe o progresso na aba Resumo (preenche automaticamente).
B17: Como ler as colunas
... B23: • Coluna ✓ — selecione o ✓ para marcar o item como revisado (fica verde).

Sheet Fundamentos
A1: AUDITORIA DE CAMPANHAS — TRÁFEGO PAGO
A2: V4 Company · Fundamentos
A3: ✓ | B3: Item | C3: Como auditar (passo a passo + pontos de atenção) | D3: Benchmark / Referência 2026 | E3: Como corrigir | F3: Criticidade | G3: Status | H3: Observações
A4: 1.1 Rastreamento e mensuração
B5: Pixel/tag instalado e disparando em todas as páginas | C5: Use o Meta Pixel Helper / Google Tag Assistant e o modo de teste de eventos. Navegue por home, LP, checkout e obrigado conferindo se o pixel carrega e o PageView dispara. | D5: 100% das páginas com disparo confirmado | E5: Reinstale via GTM ou tag nativa; corrija o disparo nas páginas que faltam antes de subir verba. | F5: Crítico | G5: Pendente
B6: Eventos de conversão configurados e validados | C6: No gerenciador de eventos, confira se Lead/Compra/AddToCart disparam com os parâmetros corretos (valor, moeda). Faça uma conversão teste e veja se aparece em tempo real. | D6: Evento principal + valor/moeda preenchidos | E6: Configure os eventos faltantes; padronize o evento-chave do funil (ex: Lead) e marque como conversão principal. | F6: Crítico | G6: Pendente
B7: Conversões server-side ativas (Meta CAPI / Google Enhanced Conversions) | C7: Verifique CAPI no Meta (deduplicação por event_id) e Enhanced Conversions no Google. Cheque a qualidade do match/EMQ. | D7: EMQ Meta >= 6; Enhanced Conversions ativo | E7: Ative server-side; garanta event_id para deduplicar; envie dados de 1ª parte (e-mail/telefone hasheados). | F7: Importante | G7: Pendente
B8: UTMs padronizados em todos os links | C8: Liste os anúncios e confira utm_source/medium/campaign/content consistentes e sem espaços/maiúsculas quebradas. Cruze com o GA4. | D8: Padrão único documentado | E8: Defina convenção de UTM e aplique via planilha/gerador; corrija links divergentes. | F8: Importante | G8: Pendente
B9: Consentimento / Consent Mode v2 (LGPD) | C9: Confirme banner de cookies e Consent Mode v2 enviando sinais de consentimento. Sem isso, mensuração e modelagem ficam comprometidas. | D9: Consent Mode v2 ativo | E9: Implemente CMP + Consent Mode v2; ajuste o GTM para respeitar o consentimento. | F9: Importante | G9: Pendente
B10: Janela de atribuição definida e coerente | C10: Veja a janela usada (ex: 7d clique / 1d visualização no Meta) e se é a mesma referência usada no relatório ao cliente. | D10: Mesma janela na conta e no report | E10: Padronize a janela; alinhe a leitura de resultado com o cliente para não comparar bases diferentes. | F10: Bom ter | G10: Pendente
A11: 1.2 Estrutura e nomenclatura da conta
B12: Padrão de nomenclatura consistente | C12: Abra campanhas/conjuntos/anúncios e veja se há padrão legível (objetivo, público, criativo). Nomes aleatórios travam a leitura. | D12: Convenção única em 100% dos itens | E12: Aplique nomenclatura padrão (ex: [Funil]_[Publico]_[Oferta]_[Criativo]). | F12: Importante | G12: Pendente
B13: Separação por etapa de funil (topo/meio/fundo) | C13: Confirme se prospecção, consideração e remarketing estão separados em campanhas distintas, com mensagem adequada a cada etapa. | D13: Funil segmentado | E13: Reorganize: separe aquisição de remarketing; ajuste a oferta por temperatura do público. | F13: Importante | G13: Pendente
B14: Uma conversão-objetivo clara por campanha | C14: Cada campanha deve otimizar para um único objetivo coerente com a etapa. Objetivo errado queima verba. | D14: 1 objetivo por campanha | E14: Realinhe o objetivo de otimização ao resultado de negócio (ex: Lead, Compra). | F14: Crítico | G14: Pendente
A15: 1.3 Verba e objetivo
B16: Investimento coerente com ticket e meta de CPL/CPA | C16: Calcule CPL/CPA-alvo a partir do ticket médio e da taxa de conversão. Veja se a verba comporta volume mínimo de resultados. | D16: CPA-alvo = ticket x margem permitida | E16: Reabra a meta com o cliente; ajuste verba ou oferta para o CPA fazer sentido. | F16: Crítico | G16: Pendente
B17: Distribuição aquisição vs remarketing | C17: Veja o % de verba em prospecção vs remarketing. Remarketing canibaliza se domina o orçamento. | D17: Maioria em aquisição/conversão (topo) | E17: Realoque verba para aquisição; limite remarketing ao tamanho real do público quente. | F17: Importante | G17: Pendente
B18: Orçamento sai da fase de aprendizado | C18: Confira se os conjuntos atingem o volume mínimo de conversões para sair de 'aprendizado' (Meta) ou estabilizar (Google). | D18: ~50 conversões/conjunto/semana (Meta) | E18: Consolide conjuntos; aumente verba por conjunto ou simplifique a estrutura. | F18: Importante | G18: Pendente
A19: 1.4 Oferta, criativo e mensagem
B20: Promessa do anúncio alinhada ao destino | C20: Clique nos anúncios e compare a promessa com a primeira dobra da LP. Quebra de continuidade derruba conversão. | D20: Mensagem anúncio = LP | E20: Alinhe headline e oferta do anúncio com a LP; padronize argumento e prova. | F20: Crítico | G20: Pendente
B21: Volume mínimo de variações em teste | C21: Conte criativos ativos por conjunto. Pouca variação impede aprender o que funciona. | D21: >= 3 criativos ativos por conjunto | E21: Produza novas variações (ângulo, formato, hook); estruture teste A/B. | F21: Importante | G21: Pendente
B22: Hook nos 3 primeiros segundos / primeira linha | C22: Assista aos vídeos e leia a primeira linha dos textos. O começo precisa prender. | D22: Hook claro no início | E22: Refaça aberturas; teste ganchos de dor, número, pergunta e prova. | F22: Importante | G22: Pendente
A23: 1.5 Métricas e leitura
B24: CTR dentro do aceitável | C24: Compare CTR (link) por canal com o benchmark. CTR baixo = criativo/público fracos. | D24: Meta >1% · Google Search >2-3% · TikTok >1% | E24: Troque criativo/copy; refine público; teste novos ângulos. | F24: Importante | G24: Pendente
B25: CPL/CPA dentro da meta | C25: Compare custo por resultado com o CPA-alvo do cliente, não com média genérica. | D25: <= CPA-alvo do cliente | E25: Otimize criativo, público ou LP; corte o que está acima da meta. | F25: Crítico | G25: Pendente
B26: Frequência sob controle (prospecção) | C26: Veja a frequência em campanhas de aquisição. Alta frequência cansa o público. | D26: < 3 em prospecção | E26: Amplie público, renove criativo, limite frequência. | F26: Bom ter | G26: Pendente
B27: ROAS acima da meta | C27: Para e-commerce/venda direta, compare ROAS com o break-even do cliente. | D27: > ROAS de break-even | E27: Realoque verba para campanhas/criativos com melhor ROAS; pause os negativos. | F27: Importante | G27: Pendente
B28: Rotina de otimização documentada | C28: Pergunte com que frequência a conta é otimizada e o que se olha. Sem rotina, a conta degrada. | D28: Cadência semanal mínima | E28: Crie ritual de otimização (leitura, corte, escala) e registre decisões. | F28: Bom ter | G28: Pendente

Sheet Meta Ads
A1: AUDITORIA DE CAMPANHAS — TRÁFEGO PAGO
A2: V4 Company · Meta Ads
A3: ✓ | B3: Item | C3: Como auditar (passo a passo + pontos de atenção) | D3: Benchmark / Referência 2026 | E3: Como corrigir | F3: Criticidade | G3: Status | H3: Observações
A4: 2.1 Configuração
B5: Pixel + CAPI com deduplicação | C5: No Gerenciador de Eventos, confira navegador + servidor com mesmo event_id (sem duplicar). Veja a cobertura de eventos. | D5: Deduplicação OK · EMQ >= 6 | E5: Implemente CAPI via Conversions API Gateway ou parceiro; alinhe event_id. | F5: Crítico | G5: Pendente
B6: Domínio verificado + priorização de eventos (AEM) | C6: Confira se o domínio está verificado e os 8 eventos priorizados configurados (essencial pós-iOS). | D6: Domínio verificado + eventos priorizados | E6: Verifique o domínio no Business Manager e configure a priorização de eventos. | F6: Importante | G6: Pendente
B7: Catálogo conectado (se e-commerce) | C7: Veja se o catálogo está sincronizado e sem erros, para Advantage+ Catalog e remarketing dinâmico. | D7: Catálogo sem erros | E7: Conecte/atualize o feed; corrija itens recusados. | F7: Bom ter | G7: Pendente
A8: 2.2 Estrutura e estratégia
B9: CBO vs ABO conforme maturidade | C9: Veja se usa orçamento por campanha (Advantage Campaign Budget) ou por conjunto, e se faz sentido para o volume. | D9: CBO com volume; ABO para testar | E9: Use ABO para testes controlados e CBO para escalar o que valida. | F9: Importante | G9: Pendente
B10: Advantage+ avaliado (ASC / públicos) | C10: Cheque se Advantage+ Shopping/Advantage+ Audience foi testado contra estrutura manual. | D10: ASC testado vs manual | E10: Teste ASC com verba dedicada; compare CPA contra a estrutura atual. | F10: Bom ter | G10: Pendente
B11: Posicionamentos coerentes com o criativo | C11: Veja posicionamentos automáticos vs manuais e se os criativos têm o formato certo por posicionamento. | D11: Formato por posicionamento | E11: Use Advantage+ Placements com criativos adaptados (9:16, 1:1, 4:5). | F11: Importante | G11: Pendente
A12: 2.3 Públicos
B13: Mix de públicos (nativos + lookalike + remarketing) | C13: Liste os públicos: interesses, lookalikes (a partir de compradores/leads), remarketing de site/engajamento. | D13: 3 camadas presentes | E13: Crie lookalike de melhores clientes; estruture remarketing por temperatura. | F13: Importante | G13: Pendente
B14: Exclusões para evitar sobreposição | C14: Confira se compradores/leads são excluídos da prospecção e se públicos não competem entre si. | D14: Exclusões aplicadas | E14: Adicione exclusões; consolide públicos sobrepostos. | F14: Importante | G14: Pendente
B15: Sobreposição de públicos checada | C15: Use a ferramenta de sobreposição. Públicos muito sobrepostos elevam CPM por competição interna. | D15: Sobreposição < 30% (validar) | E15: Una ou exclua públicos sobrepostos. | F15: Bom ter | G15: Pendente
A16: 2.4 Criativos
B17: Variações de texto e título suficientes | C17: Conte textos primários e títulos por anúncio. Pouca variação limita a otimização do algoritmo. | D17: >= 3 textos / 5 títulos | E17: Adicione variações; ou use Advantage+ Creative com cautela. | F17: Importante | G17: Pendente
B18: Formatos por posicionamento | C18: Veja se há 9:16 para Reels/Stories e 1:1 ou 4:5 para Feed. Criativo esticado mata performance. | D18: Criativo nativo por formato | E18: Produza versões por formato; priorize vertical para mobile. | F18: Importante | G18: Pendente
B19: UGC / criativos nativos testados | C19: Veja se há criativos no estilo orgânico/UGC, que costumam superar peças muito 'produzidas'. | D19: UGC em teste | E19: Produza UGC com creators; teste contra criativo de marca. | F19: Bom ter | G19: Pendente
B20: Legendas em vídeo (sem som) | C20: Boa parte assiste mudo. Confirme legendas embutidas. | D20: Legenda em 100% dos vídeos | E20: Adicione legendas/captions nos vídeos. | F20: Bom ter | G20: Pendente
A21: 2.5 Métricas Meta
B22: CTR (link) acima do aceitável | C22: Compare o CTR de link (não o CTR total) por anúncio. | D22: > 1% (link) | E22: Troque criativo/hook; refine público. | F22: Importante | G22: Pendente
B23: Rankings de qualidade e engajamento | C23: Veja os diagnósticos de qualidade/engajamento/conversão dos anúncios. | D23: Acima da média | E23: Pause peças abaixo da média; melhore criativo e relevância. | F23: Bom ter | G23: Pendente
B24: Frequência em prospecção | C24: Cheque a frequência em campanhas de aquisição. | D24: < 3 | E24: Renove criativo; amplie público. | F24: Bom ter | G24: Pendente
B25: CPM vs histórico | C25: Compare o CPM atual com o histórico da conta para detectar fadiga ou competição. | D25: Estável vs histórico | E25: Se subindo, renove criativo, revise públicos e sazonalidade. | F25: Bom ter | G25: Pendente

Sheet Google Ads
A1: AUDITORIA DE CAMPANHAS — TRÁFEGO PAGO
A2: V4 Company · Google Ads
A3: ✓ | B3: Item | C3: Como auditar (passo a passo + pontos de atenção) | D3: Benchmark / Referência 2026 | E3: Como corrigir | F3: Criticidade | G3: Status | H3: Observações
A4: 3.1 Configuração e conversões
B5: Conversões configuradas e marcadas como primárias | C5: Em Metas/Conversões, confira a ação principal marcada como 'primária' e as secundárias separadas. Veja se há contagem duplicada. | D5: 1 conversão primária clara | E5: Reclassifique conversões; remova duplicidades; use 'secundária' para sinais. | F5: Crítico | G5: Pendente
B6: Enhanced Conversions ativo | C6: Confirme Enhanced Conversions for Leads/Web ativo e recebendo dados de 1ª parte. | D6: Ativo e validado | E6: Implemente via GTM/API; envie e-mail/telefone hasheados. | F6: Importante | G6: Pendente
B7: Google Tag + GA4 vinculados | C7: Cheque a tag do Google disparando e o GA4 vinculado à conta de Ads. | D7: Vínculo ativo | E7: Vincule GA4 ao Ads; importe conversões do GA4 se fizer sentido. | F7: Importante | G7: Pendente
A8: 3.2 Tipos de campanha e estrutura
B9: Tipo de campanha coerente com o objetivo | C9: Veja se Search, Performance Max e Demand Gen estão sendo usados conforme intenção (fundo vs topo). | D9: Tipo certo por objetivo | E9: Ajuste o mix; não dependa só de PMax sem Search de marca/intenção. | F9: Importante | G9: Pendente
B10: Estrutura por tema/intenção | C10: Confira agrupamento lógico de campanhas/grupos por tema, evitando sobreposição de palavras. | D10: Grupos coesos | E10: Reestruture por tema; separe marca de genérico. | F10: Importante | G10: Pendente
B11: PMax com feed e sinais de público | C11: Se usa PMax, veja se há grupos de recursos completos, feed e sinais de público para guiar o algoritmo. | D11: Assets + sinais completos | E11: Enriqueça assets, feed e sinais; adicione exclusões de marca. | F11: Importante | G11: Pendente
A12: 3.3 Palavras-chave e termos
B13: Correspondências adequadas | C13: Veja o uso de exata/frase/ampla. Ampla sem Smart Bidding e sem negativas queima verba. | D13: Ampla só com Smart Bidding + negativas | E13: Ajuste correspondências; combine ampla com lances automáticos e negativas fortes. | F13: Importante | G13: Pendente
B14: Lista de negativas robusta e revisada | C14: Confira listas de palavras negativas aplicadas e atualizadas. | D14: Listas ativas e atualizadas | E14: Crie/atualize negativas; aplique listas compartilhadas. | F14: Crítico | G14: Pendente
B15: Termos de pesquisa auditados | C15: Abra o relatório de termos de pesquisa e veja se há gasto em termos irrelevantes. | D15: Revisão periódica | E15: Adicione termos ruins como negativos; capture bons termos como keywords. | F15: Importante | G15: Pendente
A16: 3.4 Qualidade e anúncios
B17: Quality Score / Ad Strength | C17: Veja o índice de qualidade das keywords e o Ad Strength dos RSAs. | D17: QS >= 7 · Ad Strength Boa/Excelente | E17: Melhore relevância anúncio-keyword-LP; reescreva RSAs. | F17: Importante | G17: Pendente
B18: RSAs completos | C18: Confira nº de títulos/descrições e pinagem coerente nos anúncios responsivos. | D18: 15 títulos / 4 descrições (ideal) | E18: Complete os ativos; teste pinagem da marca/oferta. | F18: Importante | G18: Pendente
B19: Extensões/assets ativos | C19: Cheque sitelinks, callouts, snippets, chamada, imagem e localização. | D19: >= 4 tipos de asset | E19: Adicione os assets faltantes; mantenha relevância. | F19: Bom ter | G19: Pendente
A20: 3.5 Lances e métricas
B21: Estratégia de lance coerente | C21: Veja a estratégia (Maximizar conversões, tCPA, tROAS) e se há dados suficientes para ela funcionar. | D21: Estratégia compatível com volume | E21: Comece em Maximizar conversões; migre a tCPA/tROAS com histórico. | F21: Importante | G21: Pendente
B22: CTR de Search saudável | C22: Compare o CTR das campanhas de Search. | D22: > 2-3% | E22: Melhore anúncio e relevância; revise keywords. | F22: Bom ter | G22: Pendente
B23: CPC vs benchmark do nicho | C23: Compare o CPC médio com a referência do nicho/região. | D23: Dentro do benchmark do nicho (validar) | E23: Refine keywords/qualidade; negative termos caros e irrelevantes. | F23: Bom ter | G23: Pendente
B24: Parcela de impressão e entrega | C24: Veja a parcela de impressão e o quanto se perde por orçamento e por ranking. Baixa entrega costuma ser orçamento, lance, qualidade ou público pequeno. | D24: Perda por orçamento baixa nas campanhas-chave | E24: Aumente verba onde perde por orçamento e melhore qualidade onde perde por ranking; se o objetivo permitir, amplie alcance (rede de Display/parceiros de pesquisa) com acompanhamento. | F24: Importante | G24: Pendente
B25: Programação por horários (ad scheduling) | C25: Em Configurações > Programação de anúncios, veja se a campanha roda nos dias/horários de maior conversão. Cruze com o relatório de desempenho por hora e por dia da semana. | D25: Anúncios ativos nos horários de maior conversão | E25: Configure a programação para concentrar entrega nos melhores horários/dias; aplique ajuste de lance maior nesses períodos e menor nos de baixa performance. | F25: Bom ter | G25: Pendente
B26: Recomendações e Optimization Score revisados | C26: Abra a aba Recomendações e veja o Optimization Score da conta. Avalie cada recomendação uma a uma: aplicar tudo sem critério infla gasto e amplia rede; ignorar tudo deixa otimização na mesa. | D26: Optimization Score > 80% (validar por conta) | E26: Aplique as recomendações que fazem sentido (negativas, lances, ativos de RSA) e rejeite as que só ampliam verba/rede. Registre o porquê de cada rejeição. | F26: Importante | G26: Pendente

Sheet LinkedIn Ads
A1: AUDITORIA DE CAMPANHAS — TRÁFEGO PAGO
A2: V4 Company · LinkedIn Ads
A3: ✓ | B3: Item | C3: Como auditar (passo a passo + pontos de atenção) | D3: Benchmark / Referência 2026 | E3: Como corrigir | F3: Criticidade | G3: Status | H3: Observações
A4: 4.1 Configuração
B5: Insight Tag instalada e validada | C5: Confira a Insight Tag no site e se está recebendo dados (públicos de site, conversões). | D5: Tag ativa recebendo dados | E5: Instale via GTM; valide no Campaign Manager. | F5: Crítico | G5: Pendente
B6: Conversões configuradas | C6: Veja se conversões de lead/site estão configuradas e atribuídas às campanhas. | D6: Conversão principal ativa | E6: Configure conversões; defina janela de atribuição. | F6: Importante | G6: Pendente
B7: CAPI / Conversões via API (se disponível) | C7: Cheque envio server-side de conversões para melhorar a mensuração. | D7: Ativo (quando aplicável) | E7: Implemente Conversions API do LinkedIn se a stack permitir. | F7: Bom ter | G7: Pendente
A8: 4.2 Segmentação B2B
B9: Segmentação por cargo/empresa/setor | C9: Confira se o público usa critérios B2B (cargo, senioridade, setor, tamanho da empresa) coerentes com o ICP. | D9: Segmentação aderente ao ICP | E9: Refine por função + senioridade + setor; evite só 'interesses'. | F9: Importante | G9: Pendente
B10: Audience Expansion / Audience Network conscientes | C10: Veja se Audience Expansion e LinkedIn Audience Network estão ligados e se isso é desejado (podem diluir qualidade). | D10: Decisão consciente (geralmente off no topo) | E10: Desligue Audience Network/Expansion para públicos premium; teste separado. | F10: Importante | G10: Pendente
B11: Tamanho de público adequado | C11: Cheque o tamanho estimado do público. Muito pequeno encarece e limita entrega. | D11: > 50.000 (recomendado) | E11: Amplie critérios mantendo o ICP; combine atributos. | F11: Bom ter | G11: Pendente
B12: Exclusões (clientes, concorrentes, próprios) | C12: Confira exclusão de quem já é cliente, concorrentes e colaboradores. | D12: Exclusões aplicadas | E12: Suba listas de exclusão; exclua a própria empresa. | F12: Bom ter | G12: Pendente
A13: 4.3 Formatos e oferta
B14: Lead Gen Forms vs LP | C14: Veja se usa Lead Gen Forms (menor fricção, preenchimento automático) quando o objetivo é lead. | D14: LGF para volume de lead | E14: Teste Lead Gen Forms contra LP; compare CPL e qualidade. | F14: Importante | G14: Pendente
B15: Formato adequado ao objetivo | C15: Confira o formato (Single Image, Document Ad, Video, Conversation/Message) frente ao objetivo. | D15: Formato por etapa | E15: Use Document Ads para material rico; vídeo para topo; conversa para nutrição. | F15: Bom ter | G15: Pendente
B16: Oferta compatível com topo B2B | C16: B2B raramente compra direto. Veja se a oferta é de valor (material, diagnóstico) e não venda imediata. | D16: Oferta de topo/educacional | E16: Troque venda direta por isca de valor; nutra antes de ofertar. | F16: Importante | G16: Pendente
A17: 4.4 Métricas LinkedIn
B18: CTR dentro do benchmark B2B | C18: Compare o CTR; no LinkedIn ele é naturalmente mais baixo que em redes B2C. | D18: > 0,4-0,5% (validar por formato) | E18: Melhore criativo e copy; refine público. | F18: Bom ter | G18: Pendente
B19: CPL avaliado por qualidade (SQL), não só volume | C19: CPL alto é normal. Avalie a conversão lead -> reunião -> oportunidade. | D19: Avaliar por SQL/oportunidade | E19: Integre com CRM; otimize por qualidade, não por CPL bruto. | F19: Importante | G19: Pendente
B20: CPC/CPM e fadiga | C20: Monitore CPC/CPM (altos no LinkedIn) e a frequência para detectar fadiga. | D20: Estável; frequência controlada | E20: Renove criativo; alterne formatos; pause peças cansadas. | F20: Bom ter | G20: Pendente

Sheet TikTok Ads
A1: AUDITORIA DE CAMPANHAS — TRÁFEGO PAGO
A2: V4 Company · TikTok Ads
A3: ✓ | B3: Item | C3: Como auditar (passo a passo + pontos de atenção) | D3: Benchmark / Referência 2026 | E3: Como corrigir | F3: Criticidade | G3: Status | H3: Observações
A4: 5.1 Configuração
B5: TikTok Pixel + Events API | C5: Confira o Pixel e a Events API (server-side) disparando os eventos com deduplicação. | D5: Pixel + EAPI ativos | E5: Implemente Events API; valide eventos no Events Manager. | F5: Crítico | G5: Pendente
B6: Eventos de conversão validados | C6: Faça uma conversão teste e confirme o registro do evento principal. | D6: Evento principal registrando | E6: Corrija o mapeamento de eventos; marque a conversão de otimização. | F6: Importante | G6: Pendente
B7: Atribuição configurada | C7: Veja a janela de atribuição e se está coerente com o ciclo de compra. | D7: Janela coerente | E7: Ajuste a janela; alinhe a leitura com o cliente. | F7: Bom ter | G7: Pendente
A8: 5.2 Criativos (o coração do TikTok)
B9: Criativos nativos / UGC | C9: Veja se os anúncios parecem conteúdo orgânico, não comercial. 'Anúncio de cara' performa mal no TikTok. | D9: Estética nativa/UGC | E9: Produza criativos no estilo da plataforma com creators; evite peças de marca engessadas. | F9: Crítico | G9: Pendente
B10: Spark Ads (impulsionar orgânico/creators) | C10: Cheque se há Spark Ads usando posts orgânicos ou de creators, que tendem a render mais. | D10: Spark Ads em teste | E10: Ative Spark Ads sobre os melhores orgânicos e parcerias com creators. | F10: Importante | G10: Pendente
B11: Som e texto na tela | C11: TikTok é som-on. Confirme áudio/trending sounds e legendas/texto na tela. | D11: Áudio + texto presentes | E11: Adicione trilha/trending sound e captions; sincronize com o ritmo. | F11: Importante | G11: Pendente
B12: Hook nos primeiros 1-3s | C12: Assista às aberturas. Os primeiros segundos decidem a retenção. | D12: Hook imediato | E12: Refaça aberturas; teste padrões nativos (POV, before/after, lista). | F12: Importante | G12: Pendente
B13: Volume de variações (fadiga alta) | C13: TikTok queima criativo rápido. Conte variações ativas e a frequência de troca. | D13: Renovação frequente de criativo | E13: Mantenha esteira de criativos; troque peças semanalmente. | F13: Importante | G13: Pendente
A14: 5.3 Estrutura e públicos
B15: Otimização de orçamento e estrutura simples | C15: Veja se a estrutura é enxuta (TikTok prefere simplicidade) com orçamento adequado por grupo. | D15: Estrutura enxuta + CBO | E15: Simplifique; evite fragmentar verba em muitos grupos pequenos. | F15: Bom ter | G15: Pendente
B16: Mix de públicos (amplo + lookalike + remarketing) | C16: Cheque públicos amplos, lookalikes e remarketing (engajamento/pixel). | D16: 3 camadas presentes | E16: Crie lookalike de conversores; estruture remarketing de engajamento. | F16: Importante | G16: Pendente
B17: Smart Targeting / Smart Performance avaliado | C17: Veja se as soluções automatizadas do TikTok foram testadas contra a segmentação manual. | D17: Automático testado vs manual | E17: Teste Smart Performance Campaign com verba dedicada. | F17: Bom ter | G17: Pendente
A18: 5.4 Métricas TikTok
B19: CTR saudável | C19: Compare o CTR dos anúncios. | D19: > 1% | E19: Troque hook/criativo; refine oferta. | F19: Bom ter | G19: Pendente
B20: CVR e CPA vs oferta | C20: CPM costuma ser baixo, mas a conversão depende da oferta e da LP mobile. | D20: CPA <= meta do cliente | E20: Otimize LP mobile e oferta; alinhe criativo->LP. | F20: Importante | G20: Pendente
B21: Fadiga criativa e frequência | C21: Monitore queda de CTR/aumento de CPM como sinal de fadiga. | D21: Trocar criativo ao sinal de queda | E21: Renove criativos; pause os fatigados. | F21: Bom ter | G21: Pendente
B22: Retenção de vídeo | C22: Veja o tempo médio de exibição / % de retenção dos vídeos. | D22: Retenção crescente vs base | E22: Encurte; melhore hook e ritmo; corte trechos de baixa retenção. | F22: Bom ter | G22: Pendente

Sheet Resumo
A1: RESUMO DA AUDITORIA
A2: V4 Company · preenche automaticamente conforme o Status
A3: Frente | B3: Itens | C3: OK | D3: Ajustar | E3: Crítico | F3: Pendente | G3: N/A | H3: % revisado
A4: Fundamentos | B4: =SUM(C4:G4) | C4: =COUNTIF('Fundamentos'!G:G,"OK") | D4: =COUNTIF('Fundamentos'!G:G,"Ajustar") | E4: =COUNTIF('Fundamentos'!G:G,"Crítico") | F4: =COUNTIF('Fundamentos'!G:G,"Pendente") | G4: =COUNTIF('Fundamentos'!G:G,"N/A") | H4: =IF(B4=0,0,(C4+G4)/B4)
A5: Meta Ads | B5: =SUM(C5:G5) | C5: =COUNTIF('Meta Ads'!G:G,"OK") | D5: =COUNTIF('Meta Ads'!G:G,"Ajustar") | E5: =COUNTIF('Meta Ads'!G:G,"Crítico") | F5: =COUNTIF('Meta Ads'!G:G,"Pendente") | G5: =COUNTIF('Meta Ads'!G:G,"N/A") | H5: =IF(B5=0,0,(C5+G5)/B5)
A6: Google Ads | B6: =SUM(C6:G6) | C6: =COUNTIF('Google Ads'!G:G,"OK") | D6: =COUNTIF('Google Ads'!G:G,"Ajustar") | E6: =COUNTIF('Google Ads'!G:G,"Crítico") | F6: =COUNTIF('Google Ads'!G:G,"Pendente") | G6: =COUNTIF('Google Ads'!G:G,"N/A") | H6: =IF(B6=0,0,(C6+G6)/B6)
A7: LinkedIn Ads | B7: =SUM(C7:G7) | C7: =COUNTIF('LinkedIn Ads'!G:G,"OK") | D7: =COUNTIF('LinkedIn Ads'!G:G,"Ajustar") | E7: =COUNTIF('LinkedIn Ads'!G:G,"Crítico") | F7: =COUNTIF('LinkedIn Ads'!G:G,"Pendente") | G7: =COUNTIF('LinkedIn Ads'!G:G,"N/A") | H7: =IF(B7=0,0,(C7+G7)/B7)
A8: TikTok Ads | B8: =SUM(C8:G8) | C8: =COUNTIF('TikTok Ads'!G:G,"OK") | D8: =COUNTIF('TikTok Ads'!G:G,"Ajustar") | E8: =COUNTIF('TikTok Ads'!G:G,"Crítico") | F8: =COUNTIF('TikTok Ads'!G:G,"Pendente") | G8: =COUNTIF('TikTok Ads'!G:G,"N/A") | H8: =IF(B8=0,0,(C8+G8)/B8)
A9: TOTAL | B9: =SUM(B4:B8) | C9: =SUM(C4:C8) | D9: =SUM(D4:D8) | E9: =SUM(E4:E8) | F9: =SUM(F4:F8) | G9: =SUM(G4:G8) | H9: =IF(B9=0,0,(C9+G9)/B9)

Sheet _Listas
A1: Pendente | B1: ✓
A2: OK
A3: Ajustar
A4: Crítico
A5: N/A
