Workbook

Sheet Como usar
A1: AUDITORIA DE CRIATIVOS — ANÚNCIO A ANÚNCIO
A2: V4 Company · Como usar esta auditoria
B4: Para que serve
B5: • Auditar os criativos de mídia paga peça a peça — não a conta como um todo.
B6: • Separar o que é problema de copy do que é problema de visual: a mesma peça pode ter um vídeo que prende e um texto que mata a conversão.
B7: • Mostrar quanto da verba está em criativo que deveria sair do ar.
B8: • Analisa somente o que está no ar hoje: campanha ativa e anúncio ativo. Histórico é outro trabalho.
B9: • Complementa a planilha 'Auditoria de Campanhas' (que julga conta, estrutura e mensuração). Uma não substitui a outra.
B11: Passo a passo
B12: 1. Leia a aba Critérios antes de julgar qualquer peça. É a régua — sem ela, o preenchimento vira opinião.
B13: 2. Colete APENAS o que está ativo — campanha ativa E anúncio ativo. Meta: Biblioteca de Anúncios com o filtro Ativos (pública, não precisa de acesso). Google/TikTok/LinkedIn: gerenciador do cliente em modo somente leitura, com o filtro de status aplicado.
B14: 3. Uma linha por criativo, na aba da plataforma. Preencha nome, campanha, formato e as métricas (gasto, CTR, CPL) vindas do export.
B15: 4. Ordene por gasto e audite de cima para baixo: as peças que somam ~80% da verba ATIVA são as que importam.
B16: 5. Julgue cada critério (Hook, Promessa, Prova, Objeção, CTA, Formato, Alinhamento, Legenda) como OK / Ajustar / Crítico.
... B35: • Se a peça foi coletada da Biblioteca de Anúncios, você tem a peça mas não tem a métrica dela. Julgue o qualitativo e deixe as colunas de número vazias — não estime.

Sheet Critérios
A1: AUDITORIA DE CRIATIVOS — ANÚNCIO A ANÚNCIO
A2: V4 Company · a régua de julgamento de cada peça
A3: Critério | B3: O que julga (como auditar) | C3: Benchmark / Referência 2026 | D3: Como corrigir | E3: Criticidade
A4: Escopo da auditoria
A5: Só campanha ativa e anúncio ativo entram | B5: Antes de julgar qualquer peça, confirme o status nos DOIS níveis: a campanha está ativa E o anúncio está ativo? Anúncio ativo dentro de campanha pausada não está rodando. No Meta, use o filtro Ativos da Biblioteca de Anúncios; nas demais redes, o filtro de status do gerenciador. No export, filtre por status antes de calcular qualquer percentual — gasto de campanha encerrada distorce a leitura de verba inteira. | C5: 100% das peças auditadas com campanha e anúncio ativos | D5: Remova da planilha o que estiver pausado. Se o cliente quiser a leitura do histórico (o que já foi testado), faça em documento separado e rotulado — nunca misturado aos achados da auditoria. | E5: Crítico
A6: Copy — o que o anúncio diz
A7: Hook (primeiros 0-3s / primeira linha) | B7: A peça prende antes de a pessoa rolar? Julgue o que acontece nos 3 primeiros segundos do vídeo ou na primeira linha do texto primário. Hook fraco: começa com logo, com 'olá, somos a empresa X', com contexto antes da tensão. Hook forte: entra no problema, na promessa ou numa quebra de padrão de cara. | C7: Tensão, promessa ou quebra de padrão até 3s | D7: Reescreva a abertura entrando direto na dor ou no resultado. Corte a introdução institucional. Teste 3 hooks diferentes sobre o mesmo corpo de vídeo. | E7: Crítico
A8: Promessa / oferta clara | B8: Dá pra dizer, depois de ver a peça uma vez, o que está sendo oferecido e para quem? Promessa vaga ('transforme seu negócio') não vende. Julgue também se a promessa é específica e se o mecanismo (o COMO) aparece. | C8: Promessa específica + para quem + mecanismo | D8: Troque adjetivo por especificidade: número, prazo, público. Diga o mecanismo — por que funciona — em vez de só prometer o resultado. | E8: Crítico
A9: Prova | B9: A peça sustenta o que promete? Depoimento, número, print de resultado, antes e depois, autoridade, volume de clientes. Sem prova, a promessa vira ruído. | C9: Ao menos 1 elemento de prova por peça | D9: Insira prova concreta: depoimento em vídeo, número auditável, print real. Prova genérica ('milhares de clientes') não conta. | E9: Importante
A10: Objeção tratada | B10: A peça antecipa a principal objeção do público (preço, tempo, complexidade, ceticismo, 'não é pra mim')? Anúncio de fundo de funil sem tratamento de objeção deixa o lead esfriar na LP. | C10: Objeção principal endereçada | D10: Mapeie a objeção nº1 do avatar e escreva uma variação da peça que ataca só ela. Boa fonte: perguntas do comercial e comentários dos anúncios. | E10: Importante
A11: CTA | B11: Há uma ação única, explícita e coerente com a etapa do funil? CTA duplo ('acesse o site e me chame no direct') divide a atenção. Julgue também se o CTA aparece no texto e na peça. | C11: 1 ação única, explícita, coerente com a etapa | D11: Deixe um único CTA por peça, no texto e no criativo, dizendo o que acontece depois do clique. | E11: Importante
A12: Visual — como o anúncio se apresenta
A13: Formato x posicionamento | B13: O formato da peça bate com onde ela roda? 9:16 para Reels/Stories/Shorts/TikTok, 1:1 ou 4:5 para Feed. Criativo esticado, com barra preta ou com texto cortado nas bordas queima verba em posicionamento nativo. | C13: Peça nativa por posicionamento | D13: Produza a versão vertical dedicada em vez de reaproveitar o corte de feed. Confira a área segura das bordas em Stories/Reels. | E13: Importante
A14: Legenda / assiste sem som | B14: A peça se sustenta com o som desligado? A maioria assiste mudo. Julgue legenda queimada (não a automática), texto na tela e se a mensagem sobrevive sem áudio. | C14: Legenda queimada + mensagem legível sem som | D14: Queime legenda no vídeo. Coloque a promessa em texto na tela nos primeiros segundos. | E14: Importante
A15: Qualidade e leitura visual | B15: Resolução, contraste, excesso de texto, poluição, marca ilegível no mobile. Julgue como espectador no celular, não no monitor. | C15: Legível no celular em 1 passada | D15: Simplifique: menos elementos, mais contraste, fonte maior. Teste vendo a peça em 5 polegadas. | E15: Bom ter
A16: Nativo / UGC testado | B16: Existe ao menos uma peça em linguagem orgânica (gravada no celular, depoimento, mão na câmera) competindo com a peça de marca? Em Meta e TikTok, a peça nativa costuma superar a produzida. | C16: Ao menos 1 peça UGC ativa por conjunto | D16: Produza 2 a 3 peças UGC por oferta e coloque para competir com a peça de marca no mesmo conjunto. | E16: Importante
A17: Coerência e economia da peça
A18: Alinhamento anúncio → destino | B18: A promessa do anúncio aparece na primeira dobra da página de destino, com as mesmas palavras? Quebra de promessa entre anúncio e LP é a causa mais comum de CTR bom com conversão ruim. | C18: Mesma promessa e mesmas palavras na 1ª dobra | D18: Alinhe o título da LP à promessa do anúncio, ou crie uma LP por oferta. Se o anúncio promete X e a página entrega Y, o problema não é o tráfego. | E18: Crítico
A19: Peso na verba x resultado | B19: Quanto essa peça consome e o que ela devolve. Criativo que come a maior fatia do orçamento com CTR e CPA piores que a média da conta é o achado mais caro da auditoria. | C19: Nenhuma peça acima da média de CPA com fatia dominante | D19: Corte a verba da peça ou pause. Realoque para a peça de melhor CPA e produza variações a partir dela. | E19: Crítico
A20: Variação suficiente por conjunto | B20: Quantas peças ativas competem dentro do mesmo conjunto. Peça única impede o algoritmo de aprender; excesso dilui o aprendizado e nenhuma sai da fase de aprendizagem. | C20: 3 a 5 peças ativas por conjunto | D20: Ajuste para a faixa: produza variações se houver menos de 3, pause as piores se houver mais de 5. | E20: Importante
A21: Fadiga criativa | B21: Frequência subindo com CTR caindo e CPM subindo indica peça gasta, não público errado. Julgue a curva, não o número isolado. | C21: Frequência < 3 em prospecção | D21: Substitua a peça (não só o público). Mantenha uma esteira de produção para trocar criativo antes da queda. | E21: Importante

Sheet Meta Ads
A1: AUDITORIA DE CRIATIVOS — ANÚNCIO A ANÚNCIO
A2: V4 Company · Meta Ads
A3: ✓ | B3: Anúncio (nome / ID) | C3: Campanha / Conjunto | D3: Formato | E3: Situação | F3: Gasto (R$) | G3: % da verba | H3: Impressões | I3: CTR | J3: CPL / CPA (R$) | K3: Hook (0-3s) | L3: Promessa / oferta | M3: Prova | N3: Objeção tratada | O3: CTA | P3: Formato x posicionamento | Q3: Alinhamento → destino | R3: Legenda / som off | S3: VEREDITO COPY | T3: VEREDITO VISUAL | U3: VEREDITO DA PEÇA | V3: Por quê | W3: Como corrigir | X3: Arquivo / link da peça
K4: Pendente | L4: Pendente | M4: Pendente | N4: Pendente | O4: Pendente | P4: Pendente | Q4: Pendente | R4: Pendente
K5: Pendente | L5: Pendente | M5: Pendente | N5: Pendente | O5: Pendente | P5: Pendente | Q5: Pendente | R5: Pendente
K6: Pendente | L6: Pendente | M6: Pendente | N6: Pendente | O6: Pendente | P6: Pendente | Q6: Pendente | R6: Pendente
K7: Pendente | L7: Pendente | M7: Pendente | N7: Pendente | O7: Pendente | P7: Pendente | Q7: Pendente | R7: Pendente
K8: Pendente | L8: Pendente | M8: Pendente | N8: Pendente | O8: Pendente | P8: Pendente | Q8: Pendente | R8: Pendente
K9: Pendente | L9: Pendente | M9: Pendente | N9: Pendente | O9: Pendente | P9: Pendente | Q9: Pendente | R9: Pendente
K10: Pendente | L10: Pendente | M10: Pendente | N10: Pendente | O10: Pendente | P10: Pendente | Q10: Pendente | R10: Pendente
K11: Pendente | L11: Pendente | M11: Pendente | N11: Pendente | O11: Pendente | P11: Pendente | Q11: Pendente | R11: Pendente
K12: Pendente | L12: Pendente | M12: Pendente | N12: Pendente | O12: Pendente | P12: Pendente | Q12: Pendente | R12: Pendente
K13: Pendente | L13: Pendente | M13: Pendente | N13: Pendente | O13: Pendente | P13: Pendente | Q13: Pendente | R13: Pendente
K14: Pendente | L14: Pendente | M14: Pendente | N14: Pendente | O14: Pendente | P14: Pendente | Q14: Pendente | R14: Pendente
K15: Pendente | L15: Pendente | M15: Pendente | N15: Pendente | O15: Pendente | P15: Pendente | Q15: Pendente | R15: Pendente
... K33: Pendente | L33: Pendente | M33: Pendente | N33: Pendente | O33: Pendente | P33: Pendente | Q33: Pendente | R33: Pendente

Sheet Google Ads
A1: AUDITORIA DE CRIATIVOS — ANÚNCIO A ANÚNCIO
A2: V4 Company · Google Ads
A3: ✓ | B3: Anúncio (nome / ID) | C3: Campanha / Conjunto | D3: Formato | E3: Situação | F3: Gasto (R$) | G3: % da verba | H3: Impressões | I3: CTR | J3: CPL / CPA (R$) | K3: Hook (0-3s) | L3: Promessa / oferta | M3: Prova | N3: Objeção tratada | O3: CTA | P3: Formato x posicionamento | Q3: Alinhamento → destino | R3: Legenda / som off | S3: VEREDITO COPY | T3: VEREDITO VISUAL | U3: VEREDITO DA PEÇA | V3: Por quê | W3: Como corrigir | X3: Arquivo / link da peça
K4: Pendente | L4: Pendente | M4: Pendente | N4: Pendente | O4: Pendente | P4: Pendente | Q4: Pendente | R4: Pendente
K5: Pendente | L5: Pendente | M5: Pendente | N5: Pendente | O5: Pendente | P5: Pendente | Q5: Pendente | R5: Pendente
K6: Pendente | L6: Pendente | M6: Pendente | N6: Pendente | O6: Pendente | P6: Pendente | Q6: Pendente | R6: Pendente
K7: Pendente | L7: Pendente | M7: Pendente | N7: Pendente | O7: Pendente | P7: Pendente | Q7: Pendente | R7: Pendente
K8: Pendente | L8: Pendente | M8: Pendente | N8: Pendente | O8: Pendente | P8: Pendente | Q8: Pendente | R8: Pendente
K9: Pendente | L9: Pendente | M9: Pendente | N9: Pendente | O9: Pendente | P9: Pendente | Q9: Pendente | R9: Pendente
K10: Pendente | L10: Pendente | M10: Pendente | N10: Pendente | O10: Pendente | P10: Pendente | Q10: Pendente | R10: Pendente
K11: Pendente | L11: Pendente | M11: Pendente | N11: Pendente | O11: Pendente | P11: Pendente | Q11: Pendente | R11: Pendente
K12: Pendente | L12: Pendente | M12: Pendente | N12: Pendente | O12: Pendente | P12: Pendente | Q12: Pendente | R12: Pendente
K13: Pendente | L13: Pendente | M13: Pendente | N13: Pendente | O13: Pendente | P13: Pendente | Q13: Pendente | R13: Pendente
K14: Pendente | L14: Pendente | M14: Pendente | N14: Pendente | O14: Pendente | P14: Pendente | Q14: Pendente | R14: Pendente
K15: Pendente | L15: Pendente | M15: Pendente | N15: Pendente | O15: Pendente | P15: Pendente | Q15: Pendente | R15: Pendente
... K33: Pendente | L33: Pendente | M33: Pendente | N33: Pendente | O33: Pendente | P33: Pendente | Q33: Pendente | R33: Pendente

Sheet TikTok Ads
A1: AUDITORIA DE CRIATIVOS — ANÚNCIO A ANÚNCIO
A2: V4 Company · TikTok Ads
A3: ✓ | B3: Anúncio (nome / ID) | C3: Campanha / Conjunto | D3: Formato | E3: Situação | F3: Gasto (R$) | G3: % da verba | H3: Impressões | I3: CTR | J3: CPL / CPA (R$) | K3: Hook (0-3s) | L3: Promessa / oferta | M3: Prova | N3: Objeção tratada | O3: CTA | P3: Formato x posicionamento | Q3: Alinhamento → destino | R3: Legenda / som off | S3: VEREDITO COPY | T3: VEREDITO VISUAL | U3: VEREDITO DA PEÇA | V3: Por quê | W3: Como corrigir | X3: Arquivo / link da peça
K4: Pendente | L4: Pendente | M4: Pendente | N4: Pendente | O4: Pendente | P4: Pendente | Q4: Pendente | R4: Pendente
K5: Pendente | L5: Pendente | M5: Pendente | N5: Pendente | O5: Pendente | P5: Pendente | Q5: Pendente | R5: Pendente
K6: Pendente | L6: Pendente | M6: Pendente | N6: Pendente | O6: Pendente | P6: Pendente | Q6: Pendente | R6: Pendente
K7: Pendente | L7: Pendente | M7: Pendente | N7: Pendente | O7: Pendente | P7: Pendente | Q7: Pendente | R7: Pendente
K8: Pendente | L8: Pendente | M8: Pendente | N8: Pendente | O8: Pendente | P8: Pendente | Q8: Pendente | R8: Pendente
K9: Pendente | L9: Pendente | M9: Pendente | N9: Pendente | O9: Pendente | P9: Pendente | Q9: Pendente | R9: Pendente
K10: Pendente | L10: Pendente | M10: Pendente | N10: Pendente | O10: Pendente | P10: Pendente | Q10: Pendente | R10: Pendente
K11: Pendente | L11: Pendente | M11: Pendente | N11: Pendente | O11: Pendente | P11: Pendente | Q11: Pendente | R11: Pendente
K12: Pendente | L12: Pendente | M12: Pendente | N12: Pendente | O12: Pendente | P12: Pendente | Q12: Pendente | R12: Pendente
K13: Pendente | L13: Pendente | M13: Pendente | N13: Pendente | O13: Pendente | P13: Pendente | Q13: Pendente | R13: Pendente
K14: Pendente | L14: Pendente | M14: Pendente | N14: Pendente | O14: Pendente | P14: Pendente | Q14: Pendente | R14: Pendente
K15: Pendente | L15: Pendente | M15: Pendente | N15: Pendente | O15: Pendente | P15: Pendente | Q15: Pendente | R15: Pendente
... K33: Pendente | L33: Pendente | M33: Pendente | N33: Pendente | O33: Pendente | P33: Pendente | Q33: Pendente | R33: Pendente

Sheet LinkedIn Ads
A1: AUDITORIA DE CRIATIVOS — ANÚNCIO A ANÚNCIO
A2: V4 Company · LinkedIn Ads
A3: ✓ | B3: Anúncio (nome / ID) | C3: Campanha / Conjunto | D3: Formato | E3: Situação | F3: Gasto (R$) | G3: % da verba | H3: Impressões | I3: CTR | J3: CPL / CPA (R$) | K3: Hook (0-3s) | L3: Promessa / oferta | M3: Prova | N3: Objeção tratada | O3: CTA | P3: Formato x posicionamento | Q3: Alinhamento → destino | R3: Legenda / som off | S3: VEREDITO COPY | T3: VEREDITO VISUAL | U3: VEREDITO DA PEÇA | V3: Por quê | W3: Como corrigir | X3: Arquivo / link da peça
K4: Pendente | L4: Pendente | M4: Pendente | N4: Pendente | O4: Pendente | P4: Pendente | Q4: Pendente | R4: Pendente
K5: Pendente | L5: Pendente | M5: Pendente | N5: Pendente | O5: Pendente | P5: Pendente | Q5: Pendente | R5: Pendente
K6: Pendente | L6: Pendente | M6: Pendente | N6: Pendente | O6: Pendente | P6: Pendente | Q6: Pendente | R6: Pendente
K7: Pendente | L7: Pendente | M7: Pendente | N7: Pendente | O7: Pendente | P7: Pendente | Q7: Pendente | R7: Pendente
K8: Pendente | L8: Pendente | M8: Pendente | N8: Pendente | O8: Pendente | P8: Pendente | Q8: Pendente | R8: Pendente
K9: Pendente | L9: Pendente | M9: Pendente | N9: Pendente | O9: Pendente | P9: Pendente | Q9: Pendente | R9: Pendente
K10: Pendente | L10: Pendente | M10: Pendente | N10: Pendente | O10: Pendente | P10: Pendente | Q10: Pendente | R10: Pendente
K11: Pendente | L11: Pendente | M11: Pendente | N11: Pendente | O11: Pendente | P11: Pendente | Q11: Pendente | R11: Pendente
K12: Pendente | L12: Pendente | M12: Pendente | N12: Pendente | O12: Pendente | P12: Pendente | Q12: Pendente | R12: Pendente
K13: Pendente | L13: Pendente | M13: Pendente | N13: Pendente | O13: Pendente | P13: Pendente | Q13: Pendente | R13: Pendente
K14: Pendente | L14: Pendente | M14: Pendente | N14: Pendente | O14: Pendente | P14: Pendente | Q14: Pendente | R14: Pendente
K15: Pendente | L15: Pendente | M15: Pendente | N15: Pendente | O15: Pendente | P15: Pendente | Q15: Pendente | R15: Pendente
... K33: Pendente | L33: Pendente | M33: Pendente | N33: Pendente | O33: Pendente | P33: Pendente | Q33: Pendente | R33: Pendente

Sheet Resumo
A1: RESUMO DOS CRIATIVOS
A2: V4 Company · preenche automaticamente conforme os vereditos
A3: Plataforma | B3: Peças | C3: Manter | D3: Ajustar | E3: Matar | F3: Verba analisada | G3: Verba em "Matar" | H3: % da verba em "Matar"
A4: Meta Ads | B4: =COUNTA('Meta Ads'!$B$4:$B$33) | C4: =COUNTIF('Meta Ads'!$U$4:$U$33,"Manter") | D4: =COUNTIF('Meta Ads'!$U$4:$U$33,"Ajustar") | E4: =COUNTIF('Meta Ads'!$U$4:$U$33,"Matar") | F4: =SUM('Meta Ads'!$F$4:$F$33) | G4: =SUMIF('Meta Ads'!$U$4:$U$33,"Matar",'Meta Ads'!$F$4:$F$33) | H4: =IF(F4=0,0,G4/F4)
A5: Google Ads | B5: =COUNTA('Google Ads'!$B$4:$B$33) | C5: =COUNTIF('Google Ads'!$U$4:$U$33,"Manter") | D5: =COUNTIF('Google Ads'!$U$4:$U$33,"Ajustar") | E5: =COUNTIF('Google Ads'!$U$4:$U$33,"Matar") | F5: =SUM('Google Ads'!$F$4:$F$33) | G5: =SUMIF('Google Ads'!$U$4:$U$33,"Matar",'Google Ads'!$F$4:$F$33) | H5: =IF(F5=0,0,G5/F5)
A6: TikTok Ads | B6: =COUNTA('TikTok Ads'!$B$4:$B$33) | C6: =COUNTIF('TikTok Ads'!$U$4:$U$33,"Manter") | D6: =COUNTIF('TikTok Ads'!$U$4:$U$33,"Ajustar") | E6: =COUNTIF('TikTok Ads'!$U$4:$U$33,"Matar") | F6: =SUM('TikTok Ads'!$F$4:$F$33) | G6: =SUMIF('TikTok Ads'!$U$4:$U$33,"Matar",'TikTok Ads'!$F$4:$F$33) | H6: =IF(F6=0,0,G6/F6)
A7: LinkedIn Ads | B7: =COUNTA('LinkedIn Ads'!$B$4:$B$33) | C7: =COUNTIF('LinkedIn Ads'!$U$4:$U$33,"Manter") | D7: =COUNTIF('LinkedIn Ads'!$U$4:$U$33,"Ajustar") | E7: =COUNTIF('LinkedIn Ads'!$U$4:$U$33,"Matar") | F7: =SUM('LinkedIn Ads'!$F$4:$F$33) | G7: =SUMIF('LinkedIn Ads'!$U$4:$U$33,"Matar",'LinkedIn Ads'!$F$4:$F$33) | H7: =IF(F7=0,0,G7/F7)
A8: TOTAL | B8: =SUM(B4:B7) | C8: =SUM(C4:C7) | D8: =SUM(D4:D7) | E8: =SUM(E4:E7) | F8: =SUM(F4:F7) | G8: =SUM(G4:G7) | H8: =IF(F8=0,0,G8/F8)
A10: Como ler
A11: • % da verba em "Matar" é o número que abre a conversa com o cliente: é o dinheiro parado em criativo que não deveria estar no ar.
A12: • Peças conta as linhas preenchidas na coluna "Anúncio". Se estiver menor que o esperado, alguma peça ficou sem nome.
A13: • Verba analisada é a soma do gasto das peças auditadas — não é a verba total da conta, e não inclui campanha pausada. Registre a cobertura no relatório.

Sheet _Listas
A1: Pendente | B1: ✓ | C1: Manter | D1: Ativo | E1: Vídeo 9:16
A2: OK | C2: Ajustar | D2: Pausado durante a auditoria | E2: Vídeo 4:5
A3: Ajustar | C3: Matar | E3: Vídeo 1:1
A4: Crítico | C4: N/A | E4: Vídeo 16:9
A5: N/A | E5: Imagem 9:16
E6: Imagem 4:5
E7: Imagem 1:1
E8: Imagem 16:9
E9: Carrossel
E10: Coleção
E11: Texto / Responsivo
E12: Outro
